MANIFEST.in
README.rst
setup.py
staNMF/__init__.py
staNMF/staNMF.py
staNMF/staNMF_Example.py
staNMF/staNMF_driver.py
staNMF/testing.py
staNMF.egg-info/PKG-INFO
staNMF.egg-info/SOURCES.txt
staNMF.egg-info/dependency_links.txt
staNMF.egg-info/requires.txt
staNMF.egg-info/top_level.txt
staNMF/data/WuExampleExpression.csv