Metadata-Version: 1.1
Name: staNMF
Version: 1.1
Summary: python 2.7 implementation of stability NMF (Siqi Wu 2016)
Home-page: https://github.com/greenelab/staNMF
Author: Greene Lab
Author-email: team@greenelab.com
License: LICENSE.txt
Platform: UNKNOWN
Classifier: Intended Audience :: Developers
Classifier: License :: OSI Approved :: BSD License
Classifier: Operating System :: OS Independent
Classifier: Programming Language :: Python
Classifier: Programming Language :: Python :: 2.7
Classifier: Topic :: Scientific/Engineering :: Bio-Informatics
